reactorch/Domain1D.py
reactorch/__init__.py
reactorch/common_utils.py
reactorch/import_kinetics.py
reactorch/kinetics.py
reactorch/magic_function.py
reactorch/solution.py
reactorch/thermo.py
reactorch/transport.py
reactorch-0.1.1.dist-info/LICENSE
reactorch-0.1.1.dist-info/METADATA
reactorch-0.1.1.dist-info/WHEEL
reactorch-0.1.1.dist-info/top_level.txt
reactorch-0.1.1.dist-info/RECORD
