Metadata-Version: 2.1
Name: reactorch
Version: 0.1.1
Summary: ReacTorch: A Differentiable Reacting Flow Simulation Package in PyTorch
Home-page: https://github.com/DENG-MIT/reactorch
Author: Weiqi Ji, Sili Deng
Author-email: weiqiji@mit.edu
License: MIT
Platform: UNKNOWN
